[
    {
        "name": "CellCognition",
        "biseToolUrl": "https://biii.eu/cellcognition",
        "projectUrl": "https://www.cellcognition-project.org/",
        "domains": [
            "screening",
            "bio-imaging"
        ],
        "tags": [],
        "datasets": [
            {
                "name": "idr0002",
                "link": "https://idr.openmicroscopy.org/search/?query=Name:idr0002",
                "availability": "upon request",
                "dataTypes": [
                    "TRACK"
                ]
            }
        ]
    },
    {
        "name": "CellProfiler",
        "biseToolUrl": "https://biii.eu/cellprofiler",
        "projectUrl": "http://cellprofiler.org",
        "domains": [
            "screening",
            "bio-imaging",
            "medical-imaging"
        ],
        "tags": [
            "FEATURE_EXTRACTION",
            "IMAGE_CLASSIFICATION",
            "AUTOMATED",
            "MANUAL"
        ],
        "datasets": [
            {
                "name": "idr0016",
                "link": "https://idr.openmicroscopy.org/search/?query=Name:idr0016",
                "availability": "upon request",
                "dataTypes": [
                    "FEATURE",
                    "ROI"
                ]
            },
            {
                "name": "idr0025",
                "link": "https://idr.openmicroscopy.org/search/?query=Name:idr0025",
                "availability": "contact authors",
                "dataTypes": [
                    "FEATURE",
                    "ROI"
                ]
            },
            {
                "name": "idr0033",
                "link": "https://idr.openmicroscopy.org/search/?query=Name:idr0033",
                "availability": "upon request",
                "dataTypes": [
                    "FEATURE",
                    "ROI"
                ]
            },
            {
                "name": "idr0036",
                "link": "https://idr.openmicroscopy.org/search/?query=Name:idr0036",
                "availability": "upon request",
                "dataTypes": [
                    "FEATURE"
                ]
            },
            {
                "name": "idr0002",
                "link": "https://idr.openmicroscopy.org/search/?query=Name:idr0002",
                "availability": "upon request",
                "material": [
                    {
                        "name": "Notebook",
                        "link": "https://binder.bioimagearchive.org/v2/gh/ome/omero-guide-cellprofiler/v0.4.0?filepath=notebooks/idr0002.ipynb",
                    }
                ],
                "dataTypes": [
                    "MATERIAL"
                ]
            }
        ]
    },
    {
        "name": "EBImage",
        "biseToolUrl": "https://biii.eu/ebimage",
        "projectUrl": "https://bioconductor.org/packages/EBImage",
        "domains": [
            "screening"
        ],
        "tags": [],
        "datasets": [
            {
                "name": "idr0012",
                "link": "https://idr.openmicroscopy.org/search/?query=Name:idr0012",
                "availability": "upon request",
                "dataTypes": [
                    "FEATURE",
                    "ROI"
                ]
            },
            {
                "name": "idr0017",
                "link": "https://idr.openmicroscopy.org/search/?query=Name:idr0017",
                "availability": "contact authors",
                "dataTypes": [
                    "FEATURE",
                    "ROI"
                ]
            },
            {
                "name": "idr0040",
                "link": "https://idr.openmicroscopy.org/search/?query=Name:idr0040",
                "availability": "upon request",
                "material": [
                    {
                        "name": "Notebook",
                        "link": "https://binder.bioimagearchive.org/v2/gh/ome/omero-guide-r/v0.1.0?filepath=notebooks/idr0040_Yeast_cell_growth.ipynb",
                    }
                ],
                "dataTypes": [
                    "MATERIAL"
                ]
            }
        ]
    },
    {
        "name": "Icy",
        "biseToolUrl": "",
        "projectUrl": "http://icy.bioimageanalysis.org",
        "domains": [
            "bio-imaging",
            "medical-imaging"
        ],
        "tags": [
            "STAND_ALONE",
            "MANUAL"
        ],
        "datasets": []
    },
    {
        "name": "ilastik",
        "biseToolUrl": "https://biii.eu/ilastik",
        "projectUrl": "http://www.ilastik.org",
        "domains": [
            "bio-imaging",
            "medical-imaging"
        ],
        "tags": [
            "FEATURE_EXTRACTION",
            "IMAGE_CLASSIFICATION",
            "AUTOMATED",
            "MANUAL"
        ],
        "datasets": [
            {
                "name": "idr0062",
                "link": "https://idr.openmicroscopy.org/search/?query=Name:idr0062",
                "availability": "upon request",
                "material": [
                    {
                        "name": "Notebook",
                        "link": "https://binder.bioimagearchive.org/v2/gh/ome/omero-guide-ilastik/v0.3.0?filepath=notebooks/idr0062_pixel_classification_zarr.ipynb",
                    }
                ],
                "dataTypes": [
                    "MATERIAL"
                ]
            }
        ]
    },
    {
        "name": "Fiji/ImageJ",
        "biseToolUrl": "https://biii.eu/imagej",
        "projectUrl": "https://imagej.net/",
        "domains": [
            "bio-imaging",
            "medical-imaging"
        ],
        "tags": [
            "STAND_ALONE",
            "MANUAL"
        ],
        "datasets": [
            {
                "name": "idr0038",
                "link": "https://idr.openmicroscopy.org/search/?query=Name:idr0038",
                "availability": "contact author",
                "mailto": "m.held@liverpool.ac.uk",
                "dataTypes": [
                    "OTHER"
                ]
            },
            {
                "name": "idr0010",
                "link": "https://idr.openmicroscopy.org/search/?query=Name:idr0010",
                "availability": "contact author",
                "dataTypes": [
                    "ROI",
                    "FEATURE"
                ]
            },
            {
                "name": "idr0011",
                "link": "https://idr.openmicroscopy.org/search/?query=Name:idr0011",
                "availability": "contact author",
                "dataTypes": [
                    "FEATURE"
                ]
            },
            {
                "name": "idr0026",
                "link": "https://idr.openmicroscopy.org/search/?query=Name:idr0026",
                "availability": "contact author",
                "dataTypes": [
                    "ROI",
                    "FEATURE"
                ]
            },
            {
                "name": "idr0021",
                "link": "https://idr.openmicroscopy.org/search/?query=Name:idr0021",
                "availability": "upon request",
                "material": [
                    {
                        "name": "Notebook",
                        "link": "https://binder.bioimagearchive.org/v2/gh/ome/omero-guide-fiji/v0.2.1?filepath=notebooks/idr0021.ipynb",
                    }
                ],
                "dataTypes": [
                    "MATERIAL"
                ]
            }
        ]
    },
    {
        "name": "Knime",
        "biseToolUrl": "https://biii.eu/knime",
        "projectUrl": "https://www.knime.com/",
        "domains": [
            "bio-imaging",
            "medical-imaging"
        ],
        "tags": [
            "AUTOMATED",
            "MANUAL"
        ],
        "datasets": []
    },
    {
        "name": "Mahotas",
        "biseToolUrl": "https://biii.eu/mahotas",
        "projectUrl": "http://mahotas.rtfd.io",
        "domains": [
            "bio-imaging",
            "medical-imaging",
            "marine"
        ],
        "tags": [
            "FEATURE_EXTRACTION",
            "WATERSHED"
        ],
        "datasets": [
            {
                "name": "idr0015",
                "link": "https://idr.openmicroscopy.org/search/?query=Name:idr0015",
                "availability": "upon request",
                "dataTypes": [
                    "FEATURE",
                    "ROI"
                ]
            }
        ]
    },
    {
        "name": "OMERO",
        "biseToolUrl": "https://biii.eu/omero",
        "projectUrl": "https://www.openmicroscopy.org",
        "domains": [
            "screening",
            "bio-imaging",
            "medical-imaging"
        ],
        "tags": [
            "STAND_ALONE"
        ],
        "datasets": [
            {
                "name": "idr0040",
                "link": "https://idr.openmicroscopy.org/search/?query=Name:idr0040",
                "availability": "upon request",
                "material": [
                    {
                        "name": "Notebook",
                        "link": "http://binder.bioimagearchive.org/v2/gh/ome/omero-guide-r/v0.1.0?filepath=notebooks/idr0040_Yeast_cell_growth.ipynb",
                    }
                ],
                "dataTypes": [
                    "MATERIAL"
                ]
            }
        ]
    },
    {
        "name": "Osirix",
        "biseToolUrl": "",
        "projectUrl": "https://www.osirix-viewer.com",
        "domains": [
            "medical-imaging"
        ],
        "tags": [
            "VOLUME_RENDERING",
            "STAND_ALONE"
        ],
        "datasets": []
    },
    {
        "name": "TrackMate",
        "biseToolUrl": "https://biii.eu/trackmate",
        "projectUrl": "https://imagej.net/TrackMate",
        "domains": [
            "bio-imaging",
            "medical-imaging"
        ],
        "tags": [
            "OBJECT_TRACKING"
        ],
        "datasets": [
            {
                "name": "idr0038",
                "link": "https://idr.openmicroscopy.org/search/?query=Name:idr0038",
                "availability": "upon request",
                "dataTypes": [
                    "TRACK"
                ]
            }
        ]
    },
    {
        "name": "wnd-charm",
        "biseToolUrl": "",
        "projectUrl": "https://github.com/wnd-charm/wnd-charm",
        "domains": [
            "bio-imaging",
            "medical-imaging"
        ],
        "tags": [
            "FEATURE_EXTRACTION",
            "IMAGE_CLASSIFICATION",
            "AUTOMATED"
        ],
        "datasets": []
    },
    {
        "name": "XNAT",
        "biseToolUrl": "",
        "projectUrl": "https://www.xnat.org/",
        "domains": [
            "medical-imaging"
        ],
        "tags": [
            "STAND_ALONE"
        ],
        "datasets": []
    }
]
